stua-0.1.1.dist-info/RECORD
stua-0.1.1.dist-info/top_level.txt
stua-0.1.1.dist-info/metadata.json
stua-0.1.1.dist-info/METADATA
stua-0.1.1.dist-info/WHEEL
stua-0.1.1.dist-info/DESCRIPTION.rst
stua/version.py
stua/commands.py
stua/os.py
stua/__init__.py
stua/vcs.py
