Metadata-Version: 2.0
Name: stua
Version: 0.1.1
Summary: A collection of generic python functions and classes,
